LICENSE
MANIFEST.in
README.rst
requirements.txt
setup.cfg
setup.py
qgrid/__init__.py
qgrid/_version.py
qgrid/grid.py
qgrid.egg-info/PKG-INFO
qgrid.egg-info/SOURCES.txt
qgrid.egg-info/dependency_links.txt
qgrid.egg-info/not-zip-safe
qgrid.egg-info/requires.txt
qgrid.egg-info/top_level.txt
qgrid/pd_json/__init__.py
qgrid/pd_json/json.py
qgrid/pd_json/normalize.py
qgrid/pd_json/table_schema.py
qgrid/static/00dd0ec0a16a1085e714c7906ff8fb06.png
qgrid/static/093a819138276b446611d1d2a45b98a2.png
qgrid/static/2352874b5f636ca331fe9509a2f9bdd7.gif
qgrid/static/3e4484ea8db10af1320808c8477346ea.gif
qgrid/static/40bf25799e4fec8079c7775083de09df.png
qgrid/static/4e7e3e142f3939883cd0a7e00cabdaef.png
qgrid/static/5045d474bb6f92f5c8b16a5921032c96.png
qgrid/static/5078061420272a9de48787c92fb5377d.png
qgrid/static/6ccc1ed85229f7c88b07bbbeefe5214d.gif
qgrid/static/a92d8f6c106943995720f2884634670e.gif
qgrid/static/b2c868bfc2cab12122861c8214e38724.gif
qgrid/static/d104fcf119d40c51554ddb8b377142e5.gif
qgrid/static/d10bc07005bb2d604f4905183690ac04.png
qgrid/static/ea4ebe072be75fbbea002631916836de.png
qgrid/static/extension.js
qgrid/static/index.js
qgrid/static/index.js.map
qgrid/tests/__init__.py
qgrid/tests/test_grid.py